{
  "version": [
    4,
    2
  ],
  "axesColl": [
    {
      "name": "XY",
      "type": "XYAxes",
      "isLogX": false,
      "isLogY": false,
      "noRotation": true,
      "calibrationPoints": [
        {
          "px": 79.12954711914062,
          "py": 367.29241943359375,
          "dx": "0",
          "dy": "0",
          "dz": null
        },
        {
          "px": 526.415771484375,
          "py": 367.29241943359375,
          "dx": "200",
          "dy": "0",
          "dz": null
        },
        {
          "px": 48.1439323425293,
          "py": 342.46630859375,
          "dx": "0",
          "dy": "0",
          "dz": null
        },
        {
          "px": 48.1439323425293,
          "py": 122.13032531738281,
          "dx": "0",
          "dy": "2.0",
          "dz": null
        }
      ]
    }
  ],
  "datasetColl": [
    {
      "name": "main and auxiliary winding",
      "axesName": "XY",
      "colorRGB": [
        200,
        0,
        0,
        255
      ],
      "metadataKeys": [],
      "data": [
        {
          "x": 82.0536631522033,
          "y": 97.78223844282228,
          "value": [
            1.3074921040604082,
            2.2210087205231543
          ]
        },
        {
          "x": 94.5,
          "y": 94.4090909090909,
          "value": [
            6.872759340027663,
            2.251626938061417
          ]
        },
        {
          "x": 105.5,
          "y": 91.5909090909091,
          "value": [
            11.791310102734762,
            2.277207705907647
          ]
        },
        {
          "x": 116.5,
          "y": 89.0909090909091,
          "value": [
            16.709860865441854,
            2.299900322545432
          ]
        },
        {
          "x": 127.5,
          "y": 86.45454545454545,
          "value": [
            21.628411628148946,
            2.323830718272551
          ]
        },
        {
          "x": 138.5,
          "y": 84.0909090909091,
          "value": [
            26.546962390856045,
            2.345285555821002
          ]
        },
        {
          "x": 149.5,
          "y": 81.72727272727273,
          "value": [
            31.465513153563137,
            2.366740393369453
          ]
        },
        {
          "x": 160.5,
          "y": 79.5,
          "value": [
            36.384063916270236,
            2.3869574518285708
          ]
        },
        {
          "x": 171.5,
          "y": 77.31818181818181,
          "value": [
            41.30261467897732,
            2.4067619172579104
          ]
        },
        {
          "x": 182.5,
          "y": 75.4090909090909,
          "value": [
            46.22116544168442,
            2.4240908245085824
          ]
        },
        {
          "x": 193.92857142857142,
          "y": 73.13648435043122,
          "value": [
            51.33134805228919,
            2.4447193802702545
          ]
        },
        {
          "x": 204.5,
          "y": 71.5,
          "value": [
            56.058266967098604,
            2.4595738250694827
          ]
        },
        {
          "x": 215.5,
          "y": 70.13636363636364,
          "value": [
            60.9768177298057,
            2.47195161596282
          ]
        },
        {
          "x": 226.5,
          "y": 68.86363636363636,
          "value": [
            65.8953684925128,
            2.4835042207966014
          ]
        },
        {
          "x": 237.5,
          "y": 67.54545454545455,
          "value": [
            70.81391925521989,
            2.4954694186601607
          ]
        },
        {
          "x": 248.5,
          "y": 66.5,
          "value": [
            75.73247001792699,
            2.5049590583450527
          ]
        },
        {
          "x": 259.5,
          "y": 65.63636363636364,
          "value": [
            80.65102078063408,
            2.5127983259108326
          ]
        },
        {
          "x": 270.5,
          "y": 65.22727272727273,
          "value": [
            85.56957154334117,
            2.516511663178834
          ]
        },
        {
          "x": 281.5,
          "y": 64.5,
          "value": [
            90.48812230604827,
            2.5231131516552807
          ]
        },
        {
          "x": 292.5,
          "y": 64.5,
          "value": [
            95.40667306875535,
            2.5231131516552807
          ]
        },
        {
          "x": 303.5,
          "y": 64.54545454545455,
          "value": [
            100.32522383146245,
            2.5227005586255027
          ]
        },
        {
          "x": 314.5,
          "y": 65.45454545454545,
          "value": [
            105.24377459416955,
            2.5144486980299443
          ]
        },
        {
          "x": 325.5,
          "y": 66.68181818181819,
          "value": [
            110.16232535687665,
            2.5033086862259406
          ]
        },
        {
          "x": 336.5,
          "y": 68.5,
          "value": [
            115.08087611958375,
            2.4868049650348247
          ]
        },
        {
          "x": 347.5,
          "y": 71.04545454545455,
          "value": [
            119.99942688229085,
            2.4636997553672617
          ]
        },
        {
          "x": 358.5,
          "y": 74.54545454545455,
          "value": [
            124.91797764499792,
            2.4319300920743627
          ]
        },
        {
          "x": 369.5,
          "y": 78.81818181818181,
          "value": [
            129.83652840770503,
            2.3931463472752394
          ]
        },
        {
          "x": 380.5,
          "y": 84.18181818181819,
          "value": [
            134.7550791704121,
            2.344460369761446
          ]
        },
        {
          "x": 391.5,
          "y": 90.95454545454545,
          "value": [
            139.67362993311923,
            2.282984008324538
          ]
        },
        {
          "x": 402.5,
          "y": 98.95454545454545,
          "value": [
            144.5921806958263,
            2.210367635083626
          ]
        },
        {
          "x": 412,
          "y": 108.13169642857143,
          "value": [
            148.8400199908915,
            2.1270662075313673
          ]
        },
        {
          "x": 423.16913354960707,
          "y": 155.03237120071063,
          "value": [
            153.8341972944549,
            1.7013465944683324
          ]
        },
        {
          "x": 416,
          "y": 164.30976518750248,
          "value": [
            150.6285839046032,
            1.617135256412349
          ]
        },
        {
          "x": 429,
          "y": 148.7,
          "value": [
            156.44141662416615,
            1.758825823294683
          ]
        },
        {
          "x": 439.5,
          "y": 139,
          "value": [
            161.13639689765927,
            1.8468731758492887
          ]
        },
        {
          "x": 450.5,
          "y": 133.1818181818182,
          "value": [
            166.05494766036634,
            1.8996850836608608
          ]
        },
        {
          "x": 461.5,
          "y": 132.4090909090909,
          "value": [
            170.97349842307347,
            1.9066991651670853
          ]
        },
        {
          "x": 472.5,
          "y": 137.0909090909091,
          "value": [
            175.89204918578054,
            1.8642020830999606
          ]
        },
        {
          "x": 482.5,
          "y": 146.33333333333334,
          "value": [
            180.3634589700597,
            1.7803081670451193
          ]
        },
        {
          "x": 490.5,
          "y": 157.35714285714286,
          "value": [
            183.94058679748304,
            1.6802445336804104
          ]
        },
        {
          "x": 496.5,
          "y": 168.5,
          "value": [
            186.62343266805055,
            1.579100299523426
          ]
        },
        {
          "x": 501,
          "y": 179.125,
          "value": [
            188.6355670709762,
            1.48265667881284
          ]
        },
        {
          "x": 505,
          "y": 190.5,
          "value": [
            190.42413098468785,
            1.3794052731109183
          ]
        },
        {
          "x": 513.038091376047,
          "y": 222.2222222222222,
          "value": [
            194.0182910272665,
            1.0914611819959137
          ]
        },
        {
          "x": 508.5,
          "y": 202.33333333333334,
          "value": [
            191.9891244091856,
            1.271993554358736
          ]
        },
        {
          "x": 510.5,
          "y": 209.5,
          "value": [
            192.8834063660414,
            1.2069413866637526
          ]
        },
        {
          "x": 515.9,
          "y": 237.6,
          "value": [
            195.29796764955216,
            0.9518763756550497
          ]
        },
        {
          "x": 518,
          "y": 251.125,
          "value": [
            196.2369637042508,
            0.8291093196446329
          ]
        },
        {
          "x": 519.5,
          "y": 263,
          "value": [
            196.90767517189266,
            0.7213193906151543
          ]
        },
        {
          "x": 521,
          "y": 276.1666666666667,
          "value": [
            197.57838663953453,
            0.6018049429894865
          ]
        },
        {
          "x": 523,
          "y": 294.1666666666667,
          "value": [
            198.4726685963904,
            0.438418103197435
          ]
        },
        {
          "x": 524.75,
          "y": 311.875,
          "value": [
            199.25516530863922,
            0.27767873534645826
          ]
        },
        {
          "x": 525.25,
          "y": 325.25,
          "value": [
            199.47873579785318,
            0.15627323633430867
          ]
        },
        {
          "x": 526.3,
          "y": 341.8,
          "value": [
            199.94823382520252,
            0.006048114192171994
          ]
        },
        {
          "x": 525.9349824276833,
          "y": 333.0650175723167,
          "value": [
            199.78501951077345,
            0.08533595721985421
          ]
        }
      ],
      "autoDetectionData": {
        "fgColor": [
          0,
          0,
          0
        ],
        "bgColor": [
          255,
          255,
          255
        ],
        "mask": [
          [
            31690,
            25
          ],
          [
            32248,
            55
          ],
          [
            32805,
            77
          ],
          [
            33358,
            100
          ],
          [
            33917,
            119
          ],
          [
            34480,
            133
          ],
          [
            35044,
            146
          ],
          [
            35606,
            158
          ],
          [
            36167,
            169
          ],
          [
            36732,
            178
          ],
          [
            37296,
            189
          ],
          [
            37860,
            198
          ],
          [
            38430,
            201
          ],
          [
            38997,
            209
          ],
          [
            39563,
            215
          ],
          [
            40127,
            229
          ],
          [
            40694,
            233
          ],
          [
            41260,
            238
          ],
          [
            41821,
            248
          ],
          [
            42392,
            250
          ],
          [
            42961,
            255
          ],
          [
            43522,
            161
          ],
          [
            43709,
            79
          ],
          [
            44087,
            150
          ],
          [
            44292,
            67
          ],
          [
            44649,
            151
          ],
          [
            44870,
            61
          ],
          [
            45220,
            134
          ],
          [
            45448,
            57
          ],
          [
            45790,
            121
          ],
          [
            46023,
            56
          ],
          [
            46357,
            118
          ],
          [
            46599,
            52
          ],
          [
            46926,
            113
          ],
          [
            47172,
            50
          ],
          [
            47493,
            108
          ],
          [
            47748,
            52
          ],
          [
            48057,
            105
          ],
          [
            48323,
            48
          ],
          [
            48620,
            107
          ],
          [
            48897,
            45
          ],
          [
            49186,
            107
          ],
          [
            49471,
            44
          ],
          [
            49754,
            104
          ],
          [
            50044,
            43
          ],
          [
            50323,
            104
          ],
          [
            50616,
            42
          ],
          [
            50894,
            99
          ],
          [
            51189,
            41
          ],
          [
            51464,
            95
          ],
          [
            51762,
            40
          ],
          [
            52035,
            89
          ],
          [
            52334,
            42
          ],
          [
            52607,
            82
          ],
          [
            52907,
            45
          ],
          [
            53179,
            79
          ],
          [
            53480,
            43
          ],
          [
            53751,
            72
          ],
          [
            54051,
            43
          ],
          [
            54323,
            67
          ],
          [
            54623,
            45
          ],
          [
            54894,
            60
          ],
          [
            55198,
            42
          ],
          [
            55465,
            54
          ],
          [
            55770,
            42
          ],
          [
            56036,
            54
          ],
          [
            56341,
            42
          ],
          [
            56607,
            46
          ],
          [
            56913,
            41
          ],
          [
            57178,
            43
          ],
          [
            57487,
            39
          ],
          [
            57749,
            39
          ],
          [
            58060,
            37
          ],
          [
            58320,
            36
          ],
          [
            58634,
            34
          ],
          [
            58891,
            33
          ],
          [
            59206,
            33
          ],
          [
            59462,
            28
          ],
          [
            59778,
            32
          ],
          [
            60033,
            28
          ],
          [
            60350,
            31
          ],
          [
            60604,
            23
          ],
          [
            60922,
            30
          ],
          [
            61175,
            13
          ],
          [
            61496,
            27
          ],
          [
            61746,
            5
          ],
          [
            62068,
            26
          ],
          [
            62640,
            25
          ],
          [
            63211,
            25
          ],
          [
            63782,
            25
          ],
          [
            64353,
            15
          ],
          [
            64924,
            15
          ],
          [
            65495,
            15
          ],
          [
            66066,
            15
          ],
          [
            66639,
            13
          ],
          [
            67210,
            13
          ],
          [
            67782,
            12
          ],
          [
            68353,
            12
          ],
          [
            68925,
            11
          ],
          [
            71819,
            29
          ],
          [
            72390,
            30
          ],
          [
            72961,
            33
          ],
          [
            73531,
            40
          ],
          [
            74093,
            49
          ],
          [
            74664,
            49
          ],
          [
            75235,
            53
          ],
          [
            75806,
            54
          ],
          [
            76377,
            55
          ],
          [
            76947,
            56
          ],
          [
            77516,
            58
          ],
          [
            78086,
            61
          ],
          [
            78653,
            66
          ],
          [
            79223,
            68
          ],
          [
            79787,
            76
          ],
          [
            80358,
            76
          ],
          [
            80929,
            76
          ],
          [
            81500,
            76
          ],
          [
            82065,
            82
          ],
          [
            82635,
            85
          ],
          [
            83206,
            85
          ],
          [
            83776,
            47
          ],
          [
            83828,
            34
          ],
          [
            84347,
            47
          ],
          [
            84399,
            34
          ],
          [
            84918,
            47
          ],
          [
            84970,
            35
          ],
          [
            85489,
            40
          ],
          [
            85543,
            33
          ],
          [
            86060,
            39
          ],
          [
            86117,
            30
          ],
          [
            86631,
            36
          ],
          [
            86688,
            30
          ],
          [
            87201,
            36
          ],
          [
            87259,
            32
          ],
          [
            87772,
            35
          ],
          [
            87831,
            31
          ],
          [
            88342,
            34
          ],
          [
            88404,
            29
          ],
          [
            88912,
            33
          ],
          [
            88975,
            31
          ],
          [
            89482,
            34
          ],
          [
            89546,
            31
          ],
          [
            90053,
            33
          ],
          [
            90119,
            29
          ],
          [
            90623,
            31
          ],
          [
            90690,
            29
          ],
          [
            91194,
            29
          ],
          [
            91261,
            29
          ],
          [
            91765,
            28
          ],
          [
            91833,
            28
          ],
          [
            92336,
            28
          ],
          [
            92404,
            31
          ],
          [
            92906,
            29
          ],
          [
            92976,
            30
          ],
          [
            93477,
            29
          ],
          [
            93547,
            31
          ],
          [
            94048,
            29
          ],
          [
            94120,
            29
          ],
          [
            94619,
            23
          ],
          [
            94691,
            30
          ],
          [
            95190,
            23
          ],
          [
            95262,
            30
          ],
          [
            95773,
            10
          ],
          [
            95833,
            30
          ],
          [
            96345,
            9
          ],
          [
            96404,
            30
          ],
          [
            96917,
            8
          ],
          [
            96975,
            30
          ],
          [
            97489,
            6
          ],
          [
            97548,
            30
          ],
          [
            98061,
            4
          ],
          [
            98119,
            30
          ],
          [
            98633,
            2
          ],
          [
            98693,
            27
          ],
          [
            99264,
            27
          ],
          [
            99835,
            27
          ],
          [
            100406,
            27
          ],
          [
            100977,
            28
          ],
          [
            101548,
            30
          ],
          [
            102120,
            29
          ],
          [
            102691,
            29
          ],
          [
            103262,
            30
          ],
          [
            103834,
            29
          ],
          [
            104405,
            29
          ],
          [
            104977,
            28
          ],
          [
            105548,
            28
          ],
          [
            106120,
            27
          ],
          [
            106691,
            27
          ],
          [
            107265,
            24
          ],
          [
            107836,
            25
          ],
          [
            108407,
            25
          ],
          [
            108980,
            24
          ],
          [
            109551,
            25
          ],
          [
            110123,
            24
          ],
          [
            110694,
            24
          ],
          [
            111265,
            28
          ],
          [
            111836,
            28
          ],
          [
            112407,
            29
          ],
          [
            112978,
            30
          ],
          [
            113549,
            31
          ],
          [
            114120,
            31
          ],
          [
            114691,
            31
          ],
          [
            115264,
            29
          ],
          [
            115835,
            29
          ],
          [
            116406,
            29
          ],
          [
            116977,
            29
          ],
          [
            117548,
            29
          ],
          [
            118123,
            25
          ],
          [
            118695,
            25
          ],
          [
            119266,
            25
          ],
          [
            119837,
            26
          ],
          [
            120409,
            25
          ],
          [
            120980,
            25
          ],
          [
            121551,
            25
          ],
          [
            122122,
            25
          ],
          [
            122693,
            26
          ],
          [
            123264,
            26
          ],
          [
            123835,
            26
          ],
          [
            124406,
            27
          ],
          [
            124978,
            26
          ],
          [
            125550,
            25
          ],
          [
            126123,
            23
          ],
          [
            126695,
            22
          ],
          [
            127266,
            22
          ],
          [
            127837,
            23
          ],
          [
            128409,
            22
          ],
          [
            128980,
            22
          ],
          [
            129551,
            22
          ],
          [
            130123,
            21
          ],
          [
            130694,
            21
          ],
          [
            131265,
            21
          ],
          [
            131836,
            21
          ],
          [
            132407,
            21
          ],
          [
            132978,
            21
          ],
          [
            133549,
            21
          ],
          [
            134120,
            21
          ],
          [
            134691,
            21
          ],
          [
            135262,
            21
          ],
          [
            135833,
            21
          ],
          [
            136405,
            21
          ],
          [
            136976,
            21
          ],
          [
            137546,
            22
          ],
          [
            138117,
            22
          ],
          [
            138688,
            22
          ],
          [
            139259,
            22
          ],
          [
            139830,
            22
          ],
          [
            140401,
            22
          ],
          [
            140973,
            21
          ],
          [
            141544,
            21
          ],
          [
            142115,
            21
          ],
          [
            142687,
            21
          ],
          [
            143258,
            21
          ],
          [
            143829,
            21
          ],
          [
            144400,
            21
          ],
          [
            144971,
            21
          ],
          [
            145542,
            21
          ],
          [
            146113,
            21
          ],
          [
            146684,
            21
          ],
          [
            147255,
            21
          ],
          [
            147826,
            21
          ],
          [
            148397,
            21
          ],
          [
            148968,
            21
          ],
          [
            149539,
            21
          ],
          [
            150110,
            21
          ],
          [
            150681,
            21
          ],
          [
            151252,
            21
          ],
          [
            151823,
            21
          ],
          [
            152394,
            21
          ],
          [
            152965,
            21
          ],
          [
            153536,
            21
          ],
          [
            154107,
            21
          ],
          [
            154678,
            21
          ],
          [
            155249,
            22
          ],
          [
            155820,
            22
          ],
          [
            156391,
            22
          ],
          [
            156963,
            21
          ],
          [
            157534,
            21
          ],
          [
            158105,
            21
          ],
          [
            158676,
            21
          ],
          [
            159247,
            22
          ],
          [
            159818,
            22
          ],
          [
            160390,
            21
          ],
          [
            160961,
            21
          ],
          [
            161532,
            21
          ],
          [
            162103,
            21
          ],
          [
            162674,
            21
          ],
          [
            163245,
            21
          ],
          [
            163816,
            22
          ],
          [
            164387,
            22
          ],
          [
            164958,
            22
          ],
          [
            165529,
            22
          ],
          [
            166100,
            22
          ],
          [
            166672,
            21
          ],
          [
            167243,
            21
          ],
          [
            167814,
            22
          ],
          [
            168385,
            22
          ],
          [
            168956,
            22
          ],
          [
            169527,
            22
          ],
          [
            170099,
            21
          ],
          [
            170670,
            21
          ],
          [
            171241,
            22
          ],
          [
            171812,
            22
          ],
          [
            172383,
            22
          ],
          [
            172955,
            21
          ],
          [
            173526,
            21
          ],
          [
            174097,
            21
          ],
          [
            174668,
            21
          ],
          [
            175239,
            21
          ],
          [
            175810,
            21
          ],
          [
            176381,
            21
          ],
          [
            176952,
            21
          ],
          [
            177523,
            21
          ],
          [
            178094,
            21
          ],
          [
            178665,
            21
          ],
          [
            179236,
            21
          ],
          [
            179807,
            21
          ],
          [
            180378,
            21
          ],
          [
            180949,
            21
          ],
          [
            181520,
            21
          ],
          [
            182091,
            21
          ],
          [
            182662,
            21
          ],
          [
            183233,
            21
          ],
          [
            183804,
            22
          ],
          [
            184375,
            22
          ],
          [
            184946,
            22
          ],
          [
            185517,
            22
          ],
          [
            186088,
            22
          ],
          [
            186659,
            22
          ],
          [
            187230,
            22
          ],
          [
            187801,
            22
          ],
          [
            188373,
            21
          ],
          [
            188943,
            22
          ],
          [
            189514,
            22
          ],
          [
            190085,
            22
          ],
          [
            190656,
            22
          ],
          [
            191227,
            22
          ],
          [
            191798,
            22
          ],
          [
            192369,
            22
          ],
          [
            192940,
            22
          ],
          [
            193511,
            22
          ],
          [
            194082,
            22
          ],
          [
            194653,
            22
          ],
          [
            195224,
            22
          ],
          [
            195795,
            22
          ],
          [
            196366,
            22
          ],
          [
            196947,
            12
          ],
          [
            197518,
            12
          ],
          [
            198089,
            12
          ],
          [
            198660,
            12
          ],
          [
            199231,
            12
          ],
          [
            199802,
            12
          ],
          [
            200373,
            11
          ]
        ],
        "colorDetectionMode": "fg",
        "colorDistance": 120,
        "algorithm": {
          "algoType": "AveragingWindowAlgo",
          "xStep": 10,
          "yStep": 10
        },
        "name": 1,
        "imageWidth": 571,
        "imageHeight": 418
      }
    },
    {
      "name": "main winding only",
      "axesName": "XY",
      "colorRGB": [
        200,
        0,
        0,
        255
      ],
      "metadataKeys": [],
      "data": [],
      "autoDetectionData": null
    }
  ],
  "measurementColl": []
}